LICENSE.txt
ciscosupportsdk/__init__.py
ciscosupportsdk/api/__init__.py
ciscosupportsdk/api/asd.py
ciscosupportsdk/api/bug.py
ciscosupportsdk/api/case.py
ciscosupportsdk/api/eox.py
ciscosupportsdk/api/productinformation.py
ciscosupportsdk/api/serialnumbertoinformation.py
ciscosupportsdk/api/serviceorderreturn.py
ciscosupportsdk/api/softwaresuggestion.py
ciscosupportsdk/apisession.py
ciscosupportsdk/models/__init__.py
ciscosupportsdk/models/asd.py
ciscosupportsdk/models/bug.py
ciscosupportsdk/models/case.py
ciscosupportsdk/models/common.py
ciscosupportsdk/models/eox.py
ciscosupportsdk/models/productinformation.py
ciscosupportsdk/models/serialnumbertoinformation.py
ciscosupportsdk/models/serviceorderreturn.py
ciscosupportsdk/models/softwaresuggestion.py
ciscosupportsdk/validate.py
ciscosupportsdk-0.2.1.dist-info/LICENSE.txt
ciscosupportsdk-0.2.1.dist-info/METADATA
ciscosupportsdk-0.2.1.dist-info/WHEEL
ciscosupportsdk-0.2.1.dist-info/RECORD
