Metadata-Version: 2.1
Name: ciscosupportsdk
Version: 0.2.1
Summary: Cisco Support APIs allow Cisco Partner Support Services (PSS) partners and Cisco Smart Net Total Care (SNTC) customers to programmatically access and consume Cisco Support data in the cloud in a simple, secure, and scalable manner.
Home-page: https://supermanny81.github.io/ciscosupportapi/
License: MIT
Keywords: cisco,cisco-support,python-sdk
Author: Manny Garcia
Author-email: supermanny@icloud.com
Requires-Python: >=3.9,<4.0
Classifier: License :: OSI Approved :: MIT License
Classifier: Programming Language :: Python :: 3
Classifier: Programming Language :: Python :: 3.9
Classifier: Programming Language :: Python :: 3.10
Classifier: Programming Language :: Python :: 3.11
Provides-Extra: docs
Requires-Dist: Authlib (>=1.2.1,<2.0.0)
Requires-Dist: pydantic (>=1.9.0,<2.0.0)
Requires-Dist: requests (>=2.27.1,<3.0.0)
Project-URL: Repository, https://github.com/supermanny81/ciscosupportapi
